kgl/__init__.py
kgl/grammar.py
kgl/graph.py
kgl-0.1.2.dist-info/LICENSE
kgl-0.1.2.dist-info/METADATA
kgl-0.1.2.dist-info/WHEEL
kgl-0.1.2.dist-info/RECORD
