Metadata-Version: 2.1
Name: kgl
Version: 0.1.2
Summary: Knowledge Graph Language (KGL) parser.
License: MIT
Keywords: knowledge graph,graphs
Author: James (capjamesg)
Requires-Python: >=3.8,<4.0
Classifier: License :: OSI Approved :: MIT License
Classifier: Programming Language :: Python :: 3
Classifier: Programming Language :: Python :: 3.8
Classifier: Programming Language :: Python :: 3.9
Classifier: Programming Language :: Python :: 3.10
Classifier: Programming Language :: Python :: 3.11
Classifier: Programming Language :: Python :: 3.12
Requires-Dist: lark (>=0.11.3,<0.12.0)
